Workbook
Name GrandTotal: Budget!$H$10
Name MonthlyTotals: Budget!$B$10:$G$10
Name TaxRate: Rates!$F$1

Sheet Budget
A1: Category | B1: Jan | C1: Feb | D1: Mar | E1: Apr | F1: May | G1: Jun | H1: Total | I1: Share | J1: Status | K1: Average
A2: Rent | B2: 1200 | C2: 1410 | D2: 1290 | E2: 1500 | F2: 1380 | G2: 1260 | H2: =SUM(B2:G2) -> 8040 | I2: =H2/$H$10 -> 0.09581295 | J2: =IF(H2>5000,"High",IF(H2>1000,"Medium","Low")) -> High | K2: =ROUND(AVERAGE(B2:G2),2) -> 1340
A3: Salaries | B3: 9030 | C3: 10500 | D3: 9660 | E3: 8820 | F3: 10290 | G3: 9450 | H3: =SUM(B3:G3) -> 57750 | I3: =H3/$H$10 -> 0.68820869 | J3: =IF(H3>5000,"High",IF(H3>1000,"Medium","Low")) -> High | K3: =ROUND(AVERAGE(B3:G3),2) -> 9625
A4: Travel | B4: 747.5 | C4: 682.5 | D4: 796.25 | E4: 731.25 | F4: 666.25 | G4: 780 | H4: =SUM(B4:G4) -> 4403.75 | I4: =H4/$H$10 -> 0.052479637 | J4: =IF(H4>5000,"High",IF(H4>1000,"Medium","Low")) -> Medium | K4: =ROUND(AVERAGE(B4:G4),2) -> 733.96
A5: Software | B5: 514.5 | C5: 472.5 | D5: 430.5 | E5: 504 | F5: 462 | G5: 420 | H5: =SUM(B5:G5) -> 2803.5 | I5: =H5/$H$10 -> 0.033409404 | J5: =IF(H5>5000,"High",IF(H5>1000,"Medium","Low")) -> Medium | K5: =ROUND(AVERAGE(B5:G5),2) -> 467.25
A6: Marketing | B6: 922.5 | C6: 1080 | D6: 990 | E6: 900 | F6: 1057.5 | G6: 967.5 | H6: =SUM(B6:G6) -> 5917.5 | I6: =H6/$H$10 -> 0.070519046 | J6: =IF(H6>5000,"High",IF(H6>1000,"Medium","Low")) -> High | K6: =ROUND(AVERAGE(B6:G6),2) -> 986.25
A7: Supplies | B7: 198 | C7: 180 | D7: 211.5 | E7: 193.5 | F7: 225 | G7: 207 | H7: =SUM(B7:G7) -> 1215 | I7: =H7/$H$10 -> 0.014479196 | J7: =IF(H7>5000,"High",IF(H7>1000,"Medium","Low")) -> Medium | K7: =ROUND(AVERAGE(B7:G7),2) -> 202.5
A8: Training | B8: 352.5 | C8: 322.5 | D8: 375 | E8: 345 | F8: 315 | G8: 367.5 | H8: =SUM(B8:G8) -> 2077.5 | I8: =H8/$H$10 -> 0.024757637 | J8: =IF(H8>5000,"High",IF(H8>1000,"Medium","Low")) -> Medium | K8: =ROUND(AVERAGE(B8:G8),2) -> 346.25
A9: Legal | B9: 312.5 | C9: 287.5 | D9: 262.5 | E9: 306.25 | F9: 281.25 | G9: 256.25 | H9: =SUM(B9:G9) -> 1706.25 | I9: =H9/$H$10 -> 0.020333439 | J9: =IF(H9>5000,"High",IF(H9>1000,"Medium","Low")) -> Medium | K9: =ROUND(AVERAGE(B9:G9),2) -> 284.38
A10: Total | B10: =SUM(B2:B9) -> 13277.5 | C10: =SUM(C2:C9) -> 14935 | D10: =SUM(D2:D9) -> 14015.75 | E10: =SUM(E2:E9) -> 13300 | F10: =SUM(F2:F9) -> 14677 | G10: =SUM(G2:G9) -> 13708.25 | H10: =SUM(H2:H9) -> 83913.5 | I10: =SUM(I2:I9) -> 1 | K10: =AVERAGE(K2:K9) -> 1748.1987
A12: Largest category | B12: =INDEX(A2:A9,MATCH(MAX(H2:H9),H2:H9,0)) -> Salaries
A13: Smallest category | B13: =INDEX(A2:A9,MATCH(MIN(H2:H9),H2:H9,0)) -> Supplies
A14: Categories above average | B14: =COUNTIF(H2:H9,">"&AVERAGE(H2:H9)) -> 1
A15: High-cost total | B15: =SUMIF(J2:J9,"High",H2:H9) -> 71707.5
A16: Months over 12000 | B16: =SUMPRODUCT(--(B10:G10>12000)) -> 6
A17: Growth Jan to Jun | B17: =(G10-B10)/B10 -> 0.032442101
A18: Summary | B18: ="Total: "&TEXT(H10,"#,##0.00")&" across "&COUNTA(A2:A9)&" categories" -> Total: 83,913.50 across 8 categories
A19: Quarter 1 | B19: =SUM(B10:D10) -> 42228.25
A20: Quarter 2 | B20: =SUM(E10:G10) -> 41685.25
A21: Change | B21: =IFERROR(B20/B19-1,0) -> -0.012858691
A22: Named total | B22: =GrandTotal -> 83913.5
A23: Peak month total | B23: =MAX(MonthlyTotals) -> 14935
A24: Months | B24: =COUNT(MonthlyTotals) -> 6

Sheet Rates
A1: Grade | B1: Base | C1: Bonus rate | E1: Tax | F1: 0.2
A2: A | B2: 40000 | C2: 0.05
A3: B | B3: 52000 | C3: 0.08
A4: C | B4: 64000 | C4: 0.1
A5: D | B5: 80000 | C5: 0.12
A6: E | B6: 99000 | C6: 0.15

Sheet Staff
A1: Name | B1: Dept | C1: Grade | D1: Hired | E1: Base | F1: Bonus | G1: Gross | H1: Net | I1: Tenure | J1: Initials | K1: Code
A2: Maya Chen | B2: Ops | C2: B | D2: 43831 | E2: =VLOOKUP(C2,Rates!$A$2:$C$6,2,FALSE) -> 52000 | F2: =E2*VLOOKUP(C2,Rates!$A$2:$C$6,3,FALSE) -> 4160 | G2: =E2+F2 -> 56160 | H2: =ROUND(G2*(1-TaxRate),0) -> 44928 | I2: =DATEDIF(D2,DATE(2026,1,1),"Y") -> 6 | J2: =LEFT(A2,1)&MID(A2,FIND(" ",A2)+1,1) -> MC | K2: =UPPER(LEFT(B2,3))&"-"&TEXT(ROW()-1,"000") -> OPS-001
A3: Sam Okoye | B3: Finance | C3: C | D3: 44197 | E3: =VLOOKUP(C3,Rates!$A$2:$C$6,2,FALSE) -> 64000 | F3: =E3*VLOOKUP(C3,Rates!$A$2:$C$6,3,FALSE) -> 6400 | G3: =E3+F3 -> 70400 | H3: =ROUND(G3*(1-TaxRate),0) -> 56320 | I3: =DATEDIF(D3,DATE(2026,1,1),"Y") -> 5 | J3: =LEFT(A3,1)&MID(A3,FIND(" ",A3)+1,1) -> SO | K3: =UPPER(LEFT(B3,3))&"-"&TEXT(ROW()-1,"000") -> FIN-002
A4: Priya Nair | B4: Ops | C4: A | D4: 44562 | E4: =VLOOKUP(C4,Rates!$A$2:$C$6,2,FALSE) -> 40000 | F4: =E4*VLOOKUP(C4,Rates!$A$2:$C$6,3,FALSE) -> 2000 | G4: =E4+F4 -> 42000 | H4: =ROUND(G4*(1-TaxRate),0) -> 33600 | I4: =DATEDIF(D4,DATE(2026,1,1),"Y") -> 4 | J4: =LEFT(A4,1)&MID(A4,FIND(" ",A4)+1,1) -> PN | K4: =UPPER(LEFT(B4,3))&"-"&TEXT(ROW()-1,"000") -> OPS-003
A5: Luca Rossi | B5: Sales | C5: D | D5: 43101 | E5: =VLOOKUP(C5,Rates!$A$2:$C$6,2,FALSE) -> 80000 | F5: =E5*VLOOKUP(C5,Rates!$A$2:$C$6,3,FALSE) -> 9600 | G5: =E5+F5 -> 89600 | H5: =ROUND(G5*(1-TaxRate),0) -> 71680 | I5: =DATEDIF(D5,DATE(2026,1,1),"Y") -> 8 | J5: =LEFT(A5,1)&MID(A5,FIND(" ",A5)+1,1) -> LR | K5: =UPPER(LEFT(B5,3))&"-"&TEXT(ROW()-1,"000") -> SAL-004
A6: Ana Costa | B6: Finance | C6: B | D6: 44927 | E6: =VLOOKUP(C6,Rates!$A$2:$C$6,2,FALSE) -> 52000 | F6: =E6*VLOOKUP(C6,Rates!$A$2:$C$6,3,FALSE) -> 4160 | G6: =E6+F6 -> 56160 | H6: =ROUND(G6*(1-TaxRate),0) -> 44928 | I6: =DATEDIF(D6,DATE(2026,1,1),"Y") -> 3 | J6: =LEFT(A6,1)&MID(A6,FIND(" ",A6)+1,1) -> AC | K6: =UPPER(LEFT(B6,3))&"-"&TEXT(ROW()-1,"000") -> FIN-005
A7: Jonas Weber | B7: Sales | C7: E | D7: 42370 | E7: =VLOOKUP(C7,Rates!$A$2:$C$6,2,FALSE) -> 99000 | F7: =E7*VLOOKUP(C7,Rates!$A$2:$C$6,3,FALSE) -> 14850 | G7: =E7+F7 -> 113850 | H7: =ROUND(G7*(1-TaxRate),0) -> 91080 | I7: =DATEDIF(D7,DATE(2026,1,1),"Y") -> 10 | J7: =LEFT(A7,1)&MID(A7,FIND(" ",A7)+1,1) -> JW | K7: =UPPER(LEFT(B7,3))&"-"&TEXT(ROW()-1,"000") -> SAL-006
A8: Mei Tanaka | B8: Ops | C8: C | D8: 44287 | E8: =VLOOKUP(C8,Rates!$A$2:$C$6,2,FALSE) -> 64000 | F8: =E8*VLOOKUP(C8,Rates!$A$2:$C$6,3,FALSE) -> 6400 | G8: =E8+F8 -> 70400 | H8: =ROUND(G8*(1-TaxRate),0) -> 56320 | I8: =DATEDIF(D8,DATE(2026,1,1),"Y") -> 4 | J8: =LEFT(A8,1)&MID(A8,FIND(" ",A8)+1,1) -> MT | K8: =UPPER(LEFT(B8,3))&"-"&TEXT(ROW()-1,"000") -> OPS-007
A9: Omar Haddad | B9: Sales | C9: B | D9: 45292 | E9: =VLOOKUP(C9,Rates!$A$2:$C$6,2,FALSE) -> 52000 | F9: =E9*VLOOKUP(C9,Rates!$A$2:$C$6,3,FALSE) -> 4160 | G9: =E9+F9 -> 56160 | H9: =ROUND(G9*(1-TaxRate),0) -> 44928 | I9: =DATEDIF(D9,DATE(2026,1,1),"Y") -> 2 | J9: =LEFT(A9,1)&MID(A9,FIND(" ",A9)+1,1) -> OH | K9: =UPPER(LEFT(B9,3))&"-"&TEXT(ROW()-1,"000") -> SAL-008
A10: Sofia Petrov | B10: Finance | C10: D | D10: 43466 | E10: =VLOOKUP(C10,Rates!$A$2:$C$6,2,FALSE) -> 80000 | F10: =E10*VLOOKUP(C10,Rates!$A$2:$C$6,3,FALSE) -> 9600 | G10: =E10+F10 -> 89600 | H10: =ROUND(G10*(1-TaxRate),0) -> 71680 | I10: =DATEDIF(D10,DATE(2026,1,1),"Y") -> 7 | J10: =LEFT(A10,1)&MID(A10,FIND(" ",A10)+1,1) -> SP | K10: =UPPER(LEFT(B10,3))&"-"&TEXT(ROW()-1,"000") -> FIN-009
A11: Noah Kim | B11: Ops | C11: A | D11: 45658 | E11: =VLOOKUP(C11,Rates!$A$2:$C$6,2,FALSE) -> 40000 | F11: =E11*VLOOKUP(C11,Rates!$A$2:$C$6,3,FALSE) -> 2000 | G11: =E11+F11 -> 42000 | H11: =ROUND(G11*(1-TaxRate),0) -> 33600 | I11: =DATEDIF(D11,DATE(2026,1,1),"Y") -> 1 | J11: =LEFT(A11,1)&MID(A11,FIND(" ",A11)+1,1) -> NK | K11: =UPPER(LEFT(B11,3))&"-"&TEXT(ROW()-1,"000") -> OPS-010
A13: Headcount | B13: =COUNTA(A2:A11) -> 10
A14: Payroll | B14: =SUM(G2:G11) -> 686330
A15: Average net | B15: =AVERAGE(H2:H11) -> 54906.4
A16: Ops payroll | B16: =SUMIF(B2:B11,"Ops",G2:G11) -> 210560
A17: Sales headcount | B17: =COUNTIF(B2:B11,"Sales") -> 3
A18: Finance average gross | B18: =AVERAGEIF(B2:B11,"Finance",G2:G11) -> 72053.333
A19: Senior ops | B19: =COUNTIFS(B2:B11,"Ops",I2:I11,">=3") -> 3
A20: Highest paid | B20: =INDEX(A2:A11,MATCH(MAX(G2:G11),G2:G11,0)) -> Jonas Weber
A21: Earliest hire | B21: =TEXT(MIN(D2:D11),"yyyy-mm-dd") -> 2016-01-01
A22: Latest hire | B22: =TEXT(MAX(D2:D11),"d mmm yyyy") -> 1 Jan 2025
A23: Median gross | B23: =MEDIAN(G2:G11) -> 63280
A24: Top 3 sum | B24: =LARGE(G2:G11,1)+LARGE(G2:G11,2)+LARGE(G2:G11,3) -> 293050
A25: Rank of Maya | B25: =RANK(G2,G2:G11) -> 6
A26: Net above 60k | B26: =SUMPRODUCT((H2:H11>60000)*H2:H11) -> 234440
A27: Distinct depts | B27: =SUMPRODUCT(1/COUNTIF(B2:B11,B2:B11)) -> 3
A28: Full report | B28: =B20&" earns "&TEXT(MAX(G2:G11),"$#,##0") -> Jonas Weber earns $113,850
A29: Weekday of first hire | B29: =TEXT(WEEKDAY(D2),"0")&"/"&CHOOSE(WEEKDAY(D2,2),"Mon","Tue","Wed","Thu","Fri","Sat","Sun") -> 4/Wed
A30: Months since first hire | B30: =DATEDIF(MIN(D2:D11),DATE(2026,1,1),"M") -> 120
A31: End of month | B31: =EOMONTH(D2,0)-D2 -> 30
A32: Working days | B32: =NETWORKDAYS(D2,D2+30) -> 23
A33: Sorted lookup | B33: =LOOKUP(60000,Rates!B2:B6,Rates!A2:A6) -> B

Sheet Loan
A1: Principal | B1: 250000 | D1: Month | E1: Opening | F1: Interest | G1: Principal | H1: Closing
A2: Annual rate | B2: 0.045 | D2: 1 | E2: =$B$1 -> 250000 | F2: =E2*$B$2/12 -> 937.5 | G2: =$B$4-F2 -> 974.98322 | H2: =E2-G2 -> 249025.02
A3: Years | B3: 15 | D3: 2 | E3: =H2 -> 249025.02 | F3: =E3*$B$2/12 -> 933.84381 | G3: =$B$4-F3 -> 978.63941 | H3: =E3-G3 -> 248046.38
A4: Monthly payment | B4: =-PMT(B2/12,B3*12,B1) -> 1912.4832 | D4: 3 | E4: =H3 -> 248046.38 | F4: =E4*$B$2/12 -> 930.17392 | G4: =$B$4-F4 -> 982.30931 | H4: =E4-G4 -> 247064.07
A5: Total paid | B5: =B4*B3*12 -> 344246.98 | D5: 4 | E5: =H4 -> 247064.07 | F5: =E5*$B$2/12 -> 926.49026 | G5: =$B$4-F5 -> 985.99297 | H5: =E5-G5 -> 246078.08
A6: Total interest | B6: =B5-B1 -> 94246.98 | D6: 5 | E6: =H5 -> 246078.08 | F6: =E6*$B$2/12 -> 922.79278 | G6: =$B$4-F6 -> 989.69044 | H6: =E6-G6 -> 245088.38
A7: First interest | B7: =-IPMT(B2/12,1,B3*12,B1) -> 937.5 | D7: 6 | E7: =H6 -> 245088.38 | F7: =E7*$B$2/12 -> 919.08144 | G7: =$B$4-F7 -> 993.40178 | H7: =E7-G7 -> 244094.98
A8: First principal | B8: =-PPMT(B2/12,1,B3*12,B1) -> 974.98322 | D8: 7 | E8: =H7 -> 244094.98 | F8: =E8*$B$2/12 -> 915.35619 | G8: =$B$4-F8 -> 997.12704 | H8: =E8-G8 -> 243097.86
A9: Future value of savings | B9: =FV(0.03/12,120,-200) -> 27948.284 | D9: 8 | E9: =H8 -> 243097.86 | F9: =E9*$B$2/12 -> 911.61696 | G9: =$B$4-F9 -> 1000.8663 | H9: =E9-G9 -> 242096.99
A10: Present value | B10: =PV(0.05,10,-1000) -> 7721.7349 | D10: 9 | E10: =H9 -> 242096.99 | F10: =E10*$B$2/12 -> 907.86371 | G10: =$B$4-F10 -> 1004.6195 | H10: =E10-G10 -> 241092.37
A11: Periods to payoff | B11: =NPER(B2/12,-1500,B1) -> 262.04458 | D11: 10 | E11: =H10 -> 241092.37 | F11: =E11*$B$2/12 -> 904.09639 | G11: =$B$4-F11 -> 1008.3868 | H11: =E11-G11 -> 240083.98
A12: NPV | B12: =NPV(0.08,B15:B19) -> 342.20377 | D12: 11 | E12: =H11 -> 240083.98 | F12: =E12*$B$2/12 -> 900.31494 | G12: =$B$4-F12 -> 1012.1683 | H12: =E12-G12 -> 239071.81
D13: 12 | E13: =H12 -> 239071.81 | F13: =E13*$B$2/12 -> 896.51931 | G13: =$B$4-F13 -> 1015.9639 | H13: =E13-G13 -> 238055.85
A14: Cash flows | D14: Year-end balance | E14: =H13 -> 238055.85
B15: -5000 | D15: Interest in year 1 | E15: =SUM(F2:F13) -> 11005.65
B16: 1200
B17: 1500
B18: 1800
B19: 2100
A20: IRR | B20: =IRR(B15:B19) -> 0.10982876
A21: Straight-line depreciation | B21: =SLN(10000,1000,5) -> 1800
A22: Effective rate | B22: =EFFECT(0.06,12) -> 0.061677812

Sheet Stats
A1: x | B1: y | C1: group | E1: Mean x | F1: =AVERAGE(A2:A13) -> 11.333333
A2: 2 | B2: 2.4 | C2: a | E2: Median x | F2: =MEDIAN(A2:A13) -> 11
A3: 4 | B3: 6.8 | C3: b | E3: Stdev x | F3: =STDEV(A2:A13) -> 6.3005531
A4: 5 | B4: 9.5 | C4: c | E4: Variance x | F4: =VAR(A2:A13) -> 39.69697
A5: 7 | B5: 13.9 | C5: a | E5: Pop stdev | F5: =STDEVP(A2:A13) -> 6.0323204
A6: 9 | B6: 18.3 | C6: b | E6: Min | F6: =MIN(B2:B13) -> 2.4
A7: 10 | B7: 21 | C7: c | E7: Max | F7: =MAX(B2:B13) -> 36.7
A8: 12 | B8: 25.4 | C8: a | E8: Range | F8: =MAX(B2:B13)-MIN(B2:B13) -> 34.3
A9: 13 | B9: 28.1 | C9: b | E9: Correlation | F9: =CORREL(A2:A13,B2:B13) -> 0.97120487
A10: 15 | B10: 32.5 | C10: c | E10: Slope | F10: =SLOPE(B2:B13,A2:A13) -> 1.7549618
A11: 18 | B11: 29.6 | C11: a | E11: Intercept | F11: =INTERCEPT(B2:B13,A2:A13) -> 1.6270992
A12: 20 | B12: 34 | C12: b | E12: R squared | F12: =RSQ(B2:B13,A2:A13) -> 0.9432389
A13: 21 | B13: 36.7 | C13: c | E13: Forecast at 25 | F13: =FORECAST(25,B2:B13,A2:A13) -> 45.501145
E14: 90th percentile | F14: =PERCENTILE(B2:B13,0.9) -> 33.85
E15: Quartile 1 | F15: =QUARTILE(B2:B13,1) -> 12.8
E16: Quartile 3 | F16: =QUARTILE(B2:B13,3) -> 30.325
E17: Count above mean | F17: =COUNTIF(B2:B13,">"&AVERAGE(B2:B13)) -> 6
E18: Sum group a | F18: =SUMIF(C2:C13,"a",B2:B13) -> 71.3
E19: Average group b | F19: =AVERAGEIF(C2:C13,"b",B2:B13) -> 21.8
E20: Count group c | F20: =COUNTIF(C2:C13,"c") -> 4
E21: Skew | F21: =SKEW(B2:B13) -> -0.35049791
E22: Kurtosis | F22: =KURT(B2:B13) -> -1.190242
E23: Geometric mean | F23: =GEOMEAN(A2:A13) -> 9.3489216
E24: Mode-like | F24: =SMALL(A2:A13,1) -> 2
E25: Z score of 10 | F25: =STANDARDIZE(10,AVERAGE(A2:A13),STDEV(A2:A13)) -> -0.21162163
E26: Normal cdf | F26: =_xlfn.NORM.DIST(10,AVERAGE(A2:A13),STDEV(A2:A13),TRUE) -> 0.41620112
E27: Std error | F27: =STDEV(B2:B13)/SQRT(COUNT(B2:B13)) -> 3.2865851
E28: Rounded mean | F28: =ROUND(AVERAGE(B2:B13),1) -> 21.5
E29: Ceiling | F29: =CEILING(AVERAGE(B2:B13),5) -> 25
E30: Floor | F30: =FLOOR(AVERAGE(B2:B13),5) -> 20
E31: Integer part | F31: =INT(AVERAGE(B2:B13)) -> 21
E32: Sign | F32: =SIGN(SLOPE(B2:B13,A2:A13)) -> 1
E33: Abs dev | F33: =AVEDEV(B2:B13) -> 9.5333333
E34: Dev sq | F34: =DEVSQ(B2:B13) -> 1425.8167
E35: Harmonic | F35: =HARMEAN(A2:A13) -> 7.1256117
E36: Trim mean | F36: =TRIMMEAN(B2:B13,0.2) -> 21.91
